{
  "resourceType" : "ValueSet",
  "id" : "ru-type-of-document",
  "url" : "http://fhir.ru/core/ValueSet/ru-type-of-document",
  "name" : "RuTypeOfDocument",
  "title" : "ru type of document",
  "status" : "active",
  "date" : "2021-11-16T05:43:59Z",
  "compose" : {
    "include" : [ {
      "system" : "urn:CodeSystem:type-of-document",
      "concept" : [ {
        "code" : "1",
        "display" : "Паспорт гражданина СССР",
        "definition" : ""
      }, {
        "code" : "2",
        "display" : "Загранпаспорт гражданина СССР",
        "definition" : ""
      }, {
        "code" : "3",
        "display" : "Свидетельство о рождении",
        "definition" : ""
      }, {
        "code" : "4",
        "display" : "Удостоверение личности офицера",
        "definition" : ""
      }, {
        "code" : "5",
        "display" : "Справка об освобождении из места лишения свободы",
        "definition" : ""
      }, {
        "code" : "6",
        "display" : "Паспорт Минморфлота",
        "definition" : ""
      }, {
        "code" : "7",
        "display" : "Военный билет",
        "definition" : ""
      }, {
        "code" : "8",
        "display" : "Дипломатический паспорт",
        "definition" : ""
      }, {
        "code" : "9",
        "display" : "Паспорт иностранного гражданина",
        "definition" : ""
      }, {
        "code" : "10",
        "display" : "Свидетельство о регистрации ходатайства иммигранта о признании его беженцем",
        "definition" : ""
      }, {
        "code" : "11",
        "display" : "Вид на жительство в РФ",
        "definition" : ""
      }, {
        "code" : "12",
        "display" : "Удостоверение беженца",
        "definition" : ""
      }, {
        "code" : "13",
        "display" : "Временное удостоверение личности гражданина РФ",
        "definition" : ""
      }, {
        "code" : "14",
        "display" : "Паспорт гражданина РФ",
        "definition" : ""
      }, {
        "code" : "15",
        "display" : "Загранпаспорт гражданина РФ",
        "definition" : ""
      }, {
        "code" : "16",
        "display" : "Свидетельство о рождении, выданное уполномоченным органом иностранного государства ",
        "definition" : ""
      }, {
        "code" : "17",
        "display" : "Паспорт моряка",
        "definition" : ""
      }, {
        "code" : "18",
        "display" : "Военный билет офицера запаса",
        "definition" : ""
      }, {
        "code" : "19",
        "display" : "Иные документы",
        "definition" : ""
      }, {
        "code" : "20",
        "display" : "Временное удостоверение, выданное взамен военного билета",
        "definition" : ""
      }, {
        "code" : "21",
        "display" : "Разрешение на временное проживание в РФ",
        "definition" : ""
      }, {
        "code" : "22",
        "display" : "Свидетельство о предоставлении временного убежища на территории РФ",
        "definition" : ""
      }, {
        "code" : "23",
        "display" : "Удостоверение личности военнослужащего РФ",
        "definition" : ""
      }, {
        "code" : "24",
        "display" : "Документы, подтверждающие факт регистрации по месту жительства (пребывания)",
        "definition" : ""
      }, {
        "code" : "25",
        "display" : "Свидетельство о регистрации по месту жительства",
        "definition" : ""
      }, {
        "code" : "26",
        "display" : "Вид на жительство иностранного гражданина",
        "definition" : ""
      }, {
        "code" : "27",
        "display" : "Свидетельство о регистрации по месту пребывания",
        "definition" : ""
      }, {
        "code" : "28",
        "display" : "Свидетельство о смерти",
        "definition" : ""
      } ]
    } ]
  }
}